LICENSE
MANIFEST.in
readme.md
requirement.txt
setup.py
asaloader/__init__.py
asaloader/__main__.py
asaloader/alp.py
asaloader/business.py
asaloader/cli_arg.py
asaloader/device.py
asaloader/exceptions.py
asaloader/ihex.py
asaloader/loader.py
asaloader/locale.py
asaloader.egg-info/PKG-INFO
asaloader.egg-info/SOURCES.txt
asaloader.egg-info/dependency_links.txt
asaloader.egg-info/entry_points.txt
asaloader.egg-info/not-zip-safe
asaloader.egg-info/requires.txt
asaloader.egg-info/top_level.txt
asaloader/locale/asaloader.pot
asaloader/locale/zh_TW/LC_MESSAGES/asaloader.mo
asaloader/locale/zh_TW/LC_MESSAGES/asaloader.po
utils/l10n.py