Metadata-Version: 2.1
Name: asaloader
Version: 0.5.8
Summary: The program to load binary into ASA series board.
Home-page: https://gitlab.com/MVMC-lab/hervor/asaloader
Author: MVMC-lab
Author-email: ncumvmclab@gmail.com
License: MIT
Platform: UNKNOWN
